README
setup.py
nosqlalchemy/__init__.py
nosqlalchemy/nosql.py
nosqlalchemy.egg-info/PKG-INFO
nosqlalchemy.egg-info/SOURCES.txt
nosqlalchemy.egg-info/dependency_links.txt
nosqlalchemy.egg-info/entry_points.txt
nosqlalchemy.egg-info/not-zip-safe
nosqlalchemy.egg-info/requires.txt
nosqlalchemy.egg-info/top_level.txt
nosqlalchemy/tests/__init__.py
nosqlalchemy/tests/nosqlalchemy_test.py