Metadata-Version: 1.0
Name: nosqlalchemy
Version: 0.9.2
Summary: Define loosly ordered schema for mongodb documents.
Home-page: http://blog.blacknode.net
Author: Jared Rodriguez
Author-email: jared@blacknode.net
License: UNKNOWN
Keywords: mongodb mongo nosql
Platform: UNKNOWN
